ConfMatrixCalc/__init__.py
ConfMatrixCalc/cm_base.py
ConfMatrixCalc/cm_data.py
ConfMatrixCalc/cm_display.py
ConfMatrixCalc/cm_display_format.py
ConfMatrixCalc/cm_file_json.py
ConfMatrixCalc/cm_logging.py
ConfMatrixCalc/cm_model.py
ConfMatrixCalc/cm_read_xlsx.py
ConfMatrixCalc/run_cm.py
ConfMatrixCalc-0.7.1.dist-info/LICENSE.txt
ConfMatrixCalc-0.7.1.dist-info/METADATA
ConfMatrixCalc-0.7.1.dist-info/WHEEL
ConfMatrixCalc-0.7.1.dist-info/top_level.txt
ConfMatrixCalc-0.7.1.dist-info/RECORD
