Metadata-Version: 2.1
Name: ConfMatrixCalc
Version: 0.7.1
Summary: Statistical Analysis of Phoneme Confusion Matrices
Home-page: UNKNOWN
Author: Arne Leijon
Author-email: leijon@kth.se
License: MIT
Keywords: phoneme-identification confusion-matrix Bayesian speech
Platform: UNKNOWN
Classifier: Development Status :: 4 - Beta
Classifier: Programming Language :: Python :: 3.6
Classifier: License :: OSI Approved :: MIT License
Classifier: Operating System :: OS Independent
Classifier: Intended Audience :: Science/Research
Classifier: Topic :: Scientific/Engineering :: Information Analysis
Classifier: Topic :: Multimedia :: Sound/Audio
Requires-Python: >=3.6
Requires-Dist: numpy
Requires-Dist: scipy
Requires-Dist: matplotlib
Requires-Dist: samppy
Requires-Dist: openpyxl
